chatme/__init__.py
chatme/client.py
chatme/server.py
chatme-1.0.0.dist-info/LICENSE
chatme-1.0.0.dist-info/METADATA
chatme-1.0.0.dist-info/WHEEL
chatme-1.0.0.dist-info/top_level.txt
chatme-1.0.0.dist-info/RECORD
