Metadata-Version: 2.1
Name: chatme
Version: 1.0.0
Summary: A simple Python package for terminal-based chat applications
Home-page: https://github.com/ByteBreach/chatme
Author: MrFidal
Author-email: mrfidal@proton.me
Requires-Python: >=3.6
License-File: LICENSE
